ascii_art/__init__.py
ascii_art/bar.py
ascii_art/chart.py
ascii_art/histogram.py
ascii_art-0.1.0.dist-info/DESCRIPTION.rst
ascii_art-0.1.0.dist-info/METADATA
ascii_art-0.1.0.dist-info/RECORD
ascii_art-0.1.0.dist-info/WHEEL
ascii_art-0.1.0.dist-info/metadata.json
ascii_art-0.1.0.dist-info/top_level.txt
