Metadata-Version: 1.1
Name: ascii_art
Version: 0.1.0
Summary: Ascii art for python: chart, bar, histogram.
Home-page: https://github.com/lord63/ascii_art
Author: lord63
Author-email: lord63.j@gmail.com
License: MIT
Keywords: ascii art chart bar histogram commandline cli
Platform: UNKNOWN
Classifier: Development Status :: 4 - Beta
Classifier: Operating System :: POSIX
Classifier: Operating System :: POSIX :: Linux
Classifier: License :: OSI Approved :: MIT License
Classifier: Programming Language :: Python :: 3
Classifier: Programming Language :: Python :: 3.3
Classifier: Programming Language :: Python :: 3.4
Classifier: Programming Language :: Python :: 3.5
